chromatose/__init__.py
chromatose/chromatrieve.py
chromatose/chromextract.py
chromatose/colorpicker.py
chromatose/extraction.py
chromatose/heat.py
chromatose/interpolate.py
chromatose/mapper.py
chromatose/palettes.py
chromatose/utils.py
chromatose/viz.py
chromatose/volcanoes.csv
chromatose-2.0.0.dist-info/LICENSE.md
chromatose-2.0.0.dist-info/METADATA
chromatose-2.0.0.dist-info/WHEEL
chromatose-2.0.0.dist-info/entry_points.txt
chromatose-2.0.0.dist-info/top_level.txt
chromatose-2.0.0.dist-info/RECORD
