Metadata-Version: 2.1
Name: chromatose
Version: 2.0.0
Summary: Personal palette collection, palette visualizer, interpolator, and extractor
Home-page: https://github.com/atisor73/chromatose
Download-URL: https://github.com/atisor73/chromatose/archive/v1.0.2.tar.gz
Author: Rosita Fu
Author-email: rosita.fu99@gmail.com
License: MIT
Classifier: Programming Language :: Python :: 3
Classifier: License :: OSI Approved :: MIT License
Classifier: Topic :: Scientific/Engineering :: Visualization
License-File: LICENSE.md
Requires-Dist: numpy
Requires-Dist: scipy
Requires-Dist: pandas
Requires-Dist: bokeh
